logpy/__init__.py
logpy/model/__init__.py
logpy/model/entry.py
logpy/model/log.py
excellogpy-0.1.0.dist-info/METADATA
excellogpy-0.1.0.dist-info/WHEEL
excellogpy-0.1.0.dist-info/licenses/LICENSE
excellogpy-0.1.0.dist-info/RECORD
